envoy/docs/sphinx_runner/__init__.py
envoy/docs/sphinx_runner/cmd.py
envoy/docs/sphinx_runner/exceptions.py
envoy/docs/sphinx_runner/py.typed
envoy/docs/sphinx_runner/runner.py
envoy/docs/sphinx_runner/ext/httpdomain.py
envoy/docs/sphinx_runner/ext/powershell_lexer.py
envoy/docs/sphinx_runner/ext/validating_code_block.py
envoy/docs/sphinx_runner/sphinx_tabs/__init__.py
envoy/docs/sphinx_runner/sphinx_tabs/tabs.py
envoy/docs/sphinx_runner/sphinx_tabs/static/tabs.css
envoy/docs/sphinx_runner/sphinx_tabs/static/tabs.js
envoy.docs.sphinx_runner-0.2.12.dist-info/METADATA
envoy.docs.sphinx_runner-0.2.12.dist-info/WHEEL
envoy.docs.sphinx_runner-0.2.12.dist-info/entry_points.txt
envoy.docs.sphinx_runner-0.2.12.dist-info/namespace_packages.txt
envoy.docs.sphinx_runner-0.2.12.dist-info/top_level.txt
envoy.docs.sphinx_runner-0.2.12.dist-info/RECORD
