Metadata-Version: 2.1
Name: envoy.docs.sphinx-runner
Version: 0.2.12
Summary: "Sphinx docs builder used in Envoy proxy's CI"
Home-page: https://github.com/envoyproxy/toolshed/tree/main/envoy.docs.sphinx_runner
Author: Ryan Northey
Author-email: ryan@synca.io
Maintainer: Ryan Northey
Maintainer-email: ryan@synca.io
License: Apache Software License 2.0
Requires-Python: >=3.11.0
Requires-Dist: aio.run.runner (>=0.3.4)
Requires-Dist: colorama
Requires-Dist: docutils (~=0.21)
Requires-Dist: envoy.base.utils (>=0.5.7)
Requires-Dist: packaging (>=23.0)
Requires-Dist: protobuf
Requires-Dist: pygments (>=2.18.0)
Requires-Dist: sphinx-copybutton (>=0.5.1)
Requires-Dist: sphinx-rtd-theme (>=2.0.0rc2)
Requires-Dist: sphinx (>=6.2.0)
Requires-Dist: sphinxcontrib-httpdomain
Requires-Dist: sphinxcontrib-jquery (>=3.0.0)
Requires-Dist: sphinxcontrib-serializinghtml
Requires-Dist: sphinxext-rediraffe
Requires-Dist: types-pygments
